doc_reading_mcp/__init__.py
doc_reading_mcp/__main__.py
doc_reading_mcp/doc_convert.py
doc_reading_mcp-0.1.1.dist-info/METADATA
doc_reading_mcp-0.1.1.dist-info/WHEEL
doc_reading_mcp-0.1.1.dist-info/entry_points.txt
doc_reading_mcp-0.1.1.dist-info/RECORD
