Metadata-Version: 2.4
Name: doc-reading-mcp
Version: 0.1.1
Summary: A simple doc reader and converter MCP service to pdf, docx and markdown
Author-email: MatiasFrydman <78177534+mffrydman@users.noreply.github.com>
Requires-Python: >=3.13
Requires-Dist: build>=1.2.2.post1
Requires-Dist: marker-pdf==1.6.2
Requires-Dist: mcp[cli]>=1.6.0
Requires-Dist: pypandoc>=1.15
Requires-Dist: transformers==4.50.3
Requires-Dist: twine>=6.1.0
